niutrader/__init__.py
niutrader/api.py
niutrader/clienttrader.py
niutrader/exceptions.py
niutrader/follower.py
niutrader/grid_strategies.py
niutrader/log.py
niutrader/niutrader.py
niutrader/pop_dialog_handler.py
niutrader/refresh_strategies.py
niutrader/universal_clienttrader.py
niutrader/config/__init__.py
niutrader/config/client.py
niutrader/config/global.json
niutrader/utils/__init__.py
niutrader/utils/captcha.py
niutrader/utils/misc.py
niutrader/utils/perf.py
niutrader/utils/stock.py
niutrader/utils/win_gui.py
niutrader-0.0.16.dist-info/METADATA
niutrader-0.0.16.dist-info/WHEEL
niutrader-0.0.16.dist-info/licenses/LICENSE
niutrader-0.0.16.dist-info/RECORD
