Metadata-Version: 2.1
Name: niutrader
Version: 0.0.16
Summary: 同花顺自动交易系统
Project-URL: homepage, https://github.com/axiaoqi/niutrader
Project-URL: documentation, https://github.com/axiaoqi/niutrader/blob/main/README.md
Project-URL: Bug Tracker, https://github.com/axiaoqi/niutrader/issues
Author-email: NiuGe <1091874347@qq.com>
License: MIT License
License-File: LICENSE
Classifier: License :: OSI Approved :: MIT License
Classifier: Operating System :: OS Independent
Classifier: Programming Language :: Python :: 3
Requires-Python: >=3.6
Requires-Dist: easyutils
Requires-Dist: pandas>=1.0.0
Requires-Dist: pillow
Requires-Dist: pytesseract
Requires-Dist: pywin32
Requires-Dist: pywinauto==0.6.6
Requires-Dist: urllib3
